h_vialib/__init__.py
h_vialib/_flat_dict.py
h_vialib/_params.py
h_vialib/client.py
h_vialib/configuration.py
h_vialib/exceptions.py
h_vialib/secure/__init__.py
h_vialib/secure/encryption.py
h_vialib/secure/expiry.py
h_vialib/secure/token.py
h_vialib/secure/url.py
h_vialib-1.3.2.dist-info/LICENSE
h_vialib-1.3.2.dist-info/METADATA
h_vialib-1.3.2.dist-info/WHEEL
h_vialib-1.3.2.dist-info/top_level.txt
h_vialib-1.3.2.dist-info/RECORD
