Metadata-Version: 2.2
Name: h-vialib
Version: 1.3.2
Summary: Library functions for use with Via.
Home-page: https://github.com/hypothesis/h-vialib
Project-URL: Bug Tracker, https://github.com/hypothesis/h-vialib/issues
Project-URL: Changelog, https://github.com/hypothesis/h-vialib/releases
Classifier: Programming Language :: Python :: 3
Classifier: License :: OSI Approved :: BSD License
Classifier: Intended Audience :: Developers
Requires-Python: >=3.9
License-File: LICENSE
Requires-Dist: joserfc
Requires-Dist: webob
